capital_gains/__init__.py
capital_gains/__main__.py
capital_gains/__version__.py
capital_gains/argument_parser.py
capital_gains/formatter.py
capital_gains/loader.py
capital_gains/logic.py
capital_gains/model.py
capital_gains-1.0.8.dist-info/LICENSE.txt
capital_gains-1.0.8.dist-info/METADATA
capital_gains-1.0.8.dist-info/WHEEL
capital_gains-1.0.8.dist-info/entry_points.txt
capital_gains-1.0.8.dist-info/top_level.txt
capital_gains-1.0.8.dist-info/RECORD
