Metadata-Version: 2.1
Name: capital-gains
Version: 1.0.8
Summary: Capital gains calculator
Home-page: https://github.com/nkouevda/capital-gains
Author: Nikita Kouevda
Author-email: nkouevda@gmail.com
License: MIT
License-File: LICENSE.txt
